Metadata-Version: 2.1
Name: BBT
Version: 0.0.7
Summary: BBT GAME AND SHELDON JOKES
Home-page: 
Author: Djsmanoj0000
Author-email: djsmanoj0000@gmail.com
License: MIT
Keywords: Game
Classifier: Development Status :: 5 - Production/Stable
Classifier: Intended Audience :: Education
Classifier: Operating System :: Microsoft :: Windows :: Windows 11
Classifier: License :: OSI Approved :: MIT License
Classifier: Programming Language :: Python :: 3.7
License-File: LICENCE.txt
